naren_api/__init__.py
naren_api/exception.py
naren_api/logger.py
naren_api/utils.py
naren_api/components/__init__.py
naren_api/components/data_ingestion.py
naren_api/components/data_transformation.py
naren_api/components/model_trainer.py
naren_api/pipeline/__init__.py
naren_api/pipeline/predict_pipeline.py
naren_api/pipeline/train_pipeline.py
naren_api-0.0.5.dist-info/LICENSE
naren_api-0.0.5.dist-info/METADATA
naren_api-0.0.5.dist-info/WHEEL
naren_api-0.0.5.dist-info/top_level.txt
naren_api-0.0.5.dist-info/RECORD
